MANIFEST.in
README.txt
setup.py
qode/__init__.py
qode/somePython.py
qode.egg-info/PKG-INFO
qode.egg-info/SOURCES.txt
qode.egg-info/dependency_links.txt
qode.egg-info/requires.txt
qode.egg-info/top_level.txt